Workbook

Sheet README
B2: Monthly Sales MIS Report Automation
B3: An Excel MIS reporting workbook: paste orders once, pick a month, and the whole report updates.
B5: Sheet guide
B6: About the data | C6: SAMPLE DATA. The 480 orders and the product prices are generated for demonstration (a fictional office-supplies distributor). They are not real company data.
B7: Dashboard | C7: KPI cards, sales by region and category, Top 5 salespersons, auto-written insights and charts for the month selected in the yellow cell.
B8: Monthly_Summary | C8: Full-year table of orders, units, sales, profit, margin and month-on-month growth (feeds the trend chart).
B9: Data | C9: Order records. Blue columns A-G are inputs; columns H-M are formulas (category, price and cost lookups, sales, cost, profit) filled down to row 1000.
B10: Products | C10: Product master: category, unit price and unit cost used by the lookups in the Data sheet.
B11: Lists | C11: Dropdown lists (months, regions, salespersons, categories) plus helper formulas for the Top 5 table.
B12: Data_Checks | C12: 12 automatic data-quality and reconciliation checks with PASS / REVIEW status.
B14: How to use
B15: 1. Go to the Dashboard and choose a month in the yellow dropdown (and the report year).
B16: 2. To use your own data, paste orders into Data columns A-G (below the last row). Add any new products on the Products sheet.
B17: 3. Open Data_Checks: every row should say PASS. Fix anything marked REVIEW.
B18: 4. All reports, KPIs and charts recalculate automatically - no manual copy-paste.
B20: Colour legend
B21: Blue text | C21: Input you can edit (hardcoded values and lists).
B22: Black text | C22: Formula - do not overwrite.
B23: Yellow fill | C23: Selector cells on the Dashboard (month and year).
B25: Excel skills used
B26: SUMIFS, COUNTIFS, INDEX/MATCH lookups, RANK, EOMONTH/EDATE, SUMPRODUCT, IFERROR, data validation (dropdowns), conditional formatting, charts, formula-driven KPIs and data-quality checks.

Sheet Dashboard
B2: Monthly Sales MIS Dashboard
B3: Sample data for a fictional office-supplies distributor. Change the month in the yellow cell and every number and chart updates.
B5: Report Year | C5: 2025 | E5: Select Month | F5: September | H5: Period | I5: =TEXT(C6,"dd-mmm-yyyy")&" to "&TEXT(F6,"dd-mmm-yyyy") -> 01-Sep-2025 to 30-Sep-2025
B6: Start date | C6: =DATE(C5,MATCH(F5,Lists!$A$2:$A$13,0),1) -> 45901 | E6: End date | F6: =EOMONTH(C6,0) -> 45930 | H6: Prev. month start | I6: =EDATE(C6,-1) -> 45870
B8: Total Sales | D8: Total Profit | F8: Profit Margin | H8: Orders | J8: Avg Order Value | L8: Sales vs Prev. Month
B9: =SUMIFS(Data!$K$2:$K$1000,Data!$B$2:$B$1000,">="&$C$6,Data!$B$2:$B$1000,"<="&$F$6) -> 1598769 | D9: =SUMIFS(Data!$M$2:$M$1000,Data!$B$2:$B$1000,">="&$C$6,Data!$B$2:$B$1000,"<="&$F$6) -> 373269 | F9: =IF(B9=0,0,D9/B9) -> 0.23347275 | H9: =COUNTIFS(Data!$B$2:$B$1000,">="&$C$6,Data!$B$2:$B$1000,"<="&$F$6) -> 43 | J9: =IF(H9=0,0,B9/H9) -> 37180.674 | L9: =IF(SUMIFS(Data!$K$2:$K$1000,Data!$B$2:$B$1000,">="&$I$6,Data!$B$2:$B$1000,"<="&EOMONTH($I$6,0))=0,"N/A",B9/SUMIFS(Data!$K$2:$K$1000,Data!$B$2:$B$1000,">="&$I$6,Data!$B$2:$B$1000,"<="&EOMONTH($I$6,0))-1) -> 0.087476265
B12: Sales by Region | H12: Sales by Category
B13: Region | C13: Sales (₹) | D13: Profit (₹) | E13: Margin % | F13: Share of Sales | H13: Category | I13: Sales (₹) | J13: Profit (₹) | K13: Margin % | L13: Share of Sales
B14: =Lists!B2 -> North | C14: =SUMIFS(Data!$K$2:$K$1000,Data!$C$2:$C$1000,$B14,Data!$B$2:$B$1000,">="&$C$6,Data!$B$2:$B$1000,"<="&$F$6) -> 733193 | D14: =SUMIFS(Data!$M$2:$M$1000,Data!$C$2:$C$1000,$B14,Data!$B$2:$B$1000,">="&$C$6,Data!$B$2:$B$1000,"<="&$F$6) -> 174723 | E14: =IF(C14=0,0,D14/C14) -> 0.23830424 | F14: =IF($C$18=0,0,C14/$C$18) -> 0.45859846 | H14: =Lists!E2 -> Stationery | I14: =SUMIFS(Data!$K$2:$K$1000,Data!$H$2:$H$1000,$H14,Data!$B$2:$B$1000,">="&$C$6,Data!$B$2:$B$1000,"<="&$F$6) -> 422879 | J14: =SUMIFS(Data!$M$2:$M$1000,Data!$H$2:$H$1000,$H14,Data!$B$2:$B$1000,">="&$C$6,Data!$B$2:$B$1000,"<="&$F$6) -> 109779 | K14: =IF(I14=0,0,J14/I14) -> 0.25959908 | L14: =IF($I$18=0,0,I14/$I$18) -> 0.26450288
B15: =Lists!B3 -> South | C15: =SUMIFS(Data!$K$2:$K$1000,Data!$C$2:$C$1000,$B15,Data!$B$2:$B$1000,">="&$C$6,Data!$B$2:$B$1000,"<="&$F$6) -> 624972 | D15: =SUMIFS(Data!$M$2:$M$1000,Data!$C$2:$C$1000,$B15,Data!$B$2:$B$1000,">="&$C$6,Data!$B$2:$B$1000,"<="&$F$6) -> 148742 | E15: =IF(C15=0,0,D15/C15) -> 0.23799786 | F15: =IF($C$18=0,0,C15/$C$18) -> 0.39090826 | H15: =Lists!E3 -> Furniture | I15: =SUMIFS(Data!$K$2:$K$1000,Data!$H$2:$H$1000,$H15,Data!$B$2:$B$1000,">="&$C$6,Data!$B$2:$B$1000,"<="&$F$6) -> 315090 | J15: =SUMIFS(Data!$M$2:$M$1000,Data!$H$2:$H$1000,$H15,Data!$B$2:$B$1000,">="&$C$6,Data!$B$2:$B$1000,"<="&$F$6) -> 61690 | K15: =IF(I15=0,0,J15/I15) -> 0.19578533 | L15: =IF($I$18=0,0,I15/$I$18) -> 0.19708288
B16: =Lists!B4 -> East | C16: =SUMIFS(Data!$K$2:$K$1000,Data!$C$2:$C$1000,$B16,Data!$B$2:$B$1000,">="&$C$6,Data!$B$2:$B$1000,"<="&$F$6) -> 83074 | D16: =SUMIFS(Data!$M$2:$M$1000,Data!$C$2:$C$1000,$B16,Data!$B$2:$B$1000,">="&$C$6,Data!$B$2:$B$1000,"<="&$F$6) -> 19374 | E16: =IF(C16=0,0,D16/C16) -> 0.23321376 | F16: =IF($C$18=0,0,C16/$C$18) -> 0.051961228 | H16: =Lists!E4 -> Electronics | I16: =SUMIFS(Data!$K$2:$K$1000,Data!$H$2:$H$1000,$H16,Data!$B$2:$B$1000,">="&$C$6,Data!$B$2:$B$1000,"<="&$F$6) -> 343825 | J16: =SUMIFS(Data!$M$2:$M$1000,Data!$H$2:$H$1000,$H16,Data!$B$2:$B$1000,">="&$C$6,Data!$B$2:$B$1000,"<="&$F$6) -> 76825 | K16: =IF(I16=0,0,J16/I16) -> 0.22344216 | L16: =IF($I$18=0,0,I16/$I$18) -> 0.21505608
B17: =Lists!B5 -> West | C17: =SUMIFS(Data!$K$2:$K$1000,Data!$C$2:$C$1000,$B17,Data!$B$2:$B$1000,">="&$C$6,Data!$B$2:$B$1000,"<="&$F$6) -> 157530 | D17: =SUMIFS(Data!$M$2:$M$1000,Data!$C$2:$C$1000,$B17,Data!$B$2:$B$1000,">="&$C$6,Data!$B$2:$B$1000,"<="&$F$6) -> 30430 | E17: =IF(C17=0,0,D17/C17) -> 0.19316956 | F17: =IF($C$18=0,0,C17/$C$18) -> 0.098532058 | H17: =Lists!E5 -> Pantry | I17: =SUMIFS(Data!$K$2:$K$1000,Data!$H$2:$H$1000,$H17,Data!$B$2:$B$1000,">="&$C$6,Data!$B$2:$B$1000,"<="&$F$6) -> 516975 | J17: =SUMIFS(Data!$M$2:$M$1000,Data!$H$2:$H$1000,$H17,Data!$B$2:$B$1000,">="&$C$6,Data!$B$2:$B$1000,"<="&$F$6) -> 124975 | K17: =IF(I17=0,0,J17/I17) -> 0.24174283 | L17: =IF($I$18=0,0,I17/$I$18) -> 0.32335816
B18: Total | C18: =SUM(C14:C17) -> 1598769 | D18: =SUM(D14:D17) -> 373269 | E18: =IF(C18=0,0,D18/C18) -> 0.23347275 | F18: =SUM(F14:F17) -> 1 | H18: Total | I18: =SUM(I14:I17) -> 1598769 | J18: =SUM(J14:J17) -> 373269 | K18: =IF(I18=0,0,J18/I18) -> 0.23347275 | L18: =SUM(L14:L17) -> 1
B21: Top 5 Salespersons (selected month) | H21: Key Insights (auto-generated)
B22: Rank | C22: Salesperson | D22: Region | E22: Sales (₹) | F22: Orders | H22: ="Best region: "&INDEX(B14:B17,MATCH(MAX(C14:C17),C14:C17,0))&" (₹"&TEXT(MAX(C14:C17),"#,##0")&")" -> Best region: North (₹733,193)
B23: 1 | C23: =IF(INDEX(Lists!$F$2:$F$9,MATCH($B23,Lists!$H$2:$H$9,0))=0,"-",INDEX(Lists!$C$2:$C$9,MATCH($B23,Lists!$H$2:$H$9,0))) -> Amit Verma | D23: =IF(C23="-","-",INDEX(Lists!$D$2:$D$9,MATCH($B23,Lists!$H$2:$H$9,0))) -> North | E23: =INDEX(Lists!$F$2:$F$9,MATCH($B23,Lists!$H$2:$H$9,0)) -> 544835 | F23: =INDEX(Lists!$G$2:$G$9,MATCH($B23,Lists!$H$2:$H$9,0)) -> 12 | H23: ="Top category: "&INDEX(H14:H17,MATCH(MAX(I14:I17),I14:I17,0))&" (₹"&TEXT(MAX(I14:I17),"#,##0")&")" -> Top category: Pantry (₹516,975)
B24: 2 | C24: =IF(INDEX(Lists!$F$2:$F$9,MATCH($B24,Lists!$H$2:$H$9,0))=0,"-",INDEX(Lists!$C$2:$C$9,MATCH($B24,Lists!$H$2:$H$9,0))) -> Karan Iyer | D24: =IF(C24="-","-",INDEX(Lists!$D$2:$D$9,MATCH($B24,Lists!$H$2:$H$9,0))) -> South | E24: =INDEX(Lists!$F$2:$F$9,MATCH($B24,Lists!$H$2:$H$9,0)) -> 396817 | F24: =INDEX(Lists!$G$2:$G$9,MATCH($B24,Lists!$H$2:$H$9,0)) -> 12 | H24: ="Top salesperson: "&C23&" (₹"&TEXT(E23,"#,##0")&")" -> Top salesperson: Amit Verma (₹544,835)
B25: 3 | C25: =IF(INDEX(Lists!$F$2:$F$9,MATCH($B25,Lists!$H$2:$H$9,0))=0,"-",INDEX(Lists!$C$2:$C$9,MATCH($B25,Lists!$H$2:$H$9,0))) -> Priya Nair | D25: =IF(C25="-","-",INDEX(Lists!$D$2:$D$9,MATCH($B25,Lists!$H$2:$H$9,0))) -> South | E25: =INDEX(Lists!$F$2:$F$9,MATCH($B25,Lists!$H$2:$H$9,0)) -> 228155 | F25: =INDEX(Lists!$G$2:$G$9,MATCH($B25,Lists!$H$2:$H$9,0)) -> 4 | H25: =IF(L9="N/A","No previous-month data to compare.","Sales "&IF(L9>=0,"grew ","fell ")&TEXT(ABS(L9),"0.0%")&" compared with the previous month.") -> Sales grew 8.7% compared with the previous month.
B26: 4 | C26: =IF(INDEX(Lists!$F$2:$F$9,MATCH($B26,Lists!$H$2:$H$9,0))=0,"-",INDEX(Lists!$C$2:$C$9,MATCH($B26,Lists!$H$2:$H$9,0))) -> Neha Sharma | D26: =IF(C26="-","-",INDEX(Lists!$D$2:$D$9,MATCH($B26,Lists!$H$2:$H$9,0))) -> North | E26: =INDEX(Lists!$F$2:$F$9,MATCH($B26,Lists!$H$2:$H$9,0)) -> 188358 | F26: =INDEX(Lists!$G$2:$G$9,MATCH($B26,Lists!$H$2:$H$9,0)) -> 7
B27: 5 | C27: =IF(INDEX(Lists!$F$2:$F$9,MATCH($B27,Lists!$H$2:$H$9,0))=0,"-",INDEX(Lists!$C$2:$C$9,MATCH($B27,Lists!$H$2:$H$9,0))) -> Rohit Patil | D27: =IF(C27="-","-",INDEX(Lists!$D$2:$D$9,MATCH($B27,Lists!$H$2:$H$9,0))) -> West | E27: =INDEX(Lists!$F$2:$F$9,MATCH($B27,Lists!$H$2:$H$9,0)) -> 157530 | F27: =INDEX(Lists!$G$2:$G$9,MATCH($B27,Lists!$H$2:$H$9,0)) -> 4

Sheet Monthly_Summary
A1: Monthly Summary (full year)
A2: All figures are formulas (SUMIFS / COUNTIFS) on the Data sheet. Report year is set on the Dashboard.
A4: Month | B4: Month Start | C4: Orders | D4: Units Sold | E4: Sales (₹) | F4: Profit (₹) | G4: Margin % | H4: Sales vs Prev. Month
A5: =Lists!A2 -> January | B5: =DATE(Dashboard!$C$5,MATCH(A5,Lists!$A$2:$A$13,0),1) -> 45658 | C5: =COUNTIFS(Data!$B$2:$B$1000,">="&B5,Data!$B$2:$B$1000,"<="&EOMONTH(B5,0)) -> 22 | D5: =SUMIFS(Data!$F$2:$F$1000,Data!$B$2:$B$1000,">="&B5,Data!$B$2:$B$1000,"<="&EOMONTH(B5,0)) -> 1294 | E5: =SUMIFS(Data!$K$2:$K$1000,Data!$B$2:$B$1000,">="&B5,Data!$B$2:$B$1000,"<="&EOMONTH(B5,0)) -> 623474.5 | F5: =SUMIFS(Data!$M$2:$M$1000,Data!$B$2:$B$1000,">="&B5,Data!$B$2:$B$1000,"<="&EOMONTH(B5,0)) -> 156334.5 | G5: =IF(E5=0,0,F5/E5) -> 0.25074722 | H5: N/A
A6: =Lists!A3 -> February | B6: =DATE(Dashboard!$C$5,MATCH(A6,Lists!$A$2:$A$13,0),1) -> 45689 | C6: =COUNTIFS(Data!$B$2:$B$1000,">="&B6,Data!$B$2:$B$1000,"<="&EOMONTH(B6,0)) -> 32 | D6: =SUMIFS(Data!$F$2:$F$1000,Data!$B$2:$B$1000,">="&B6,Data!$B$2:$B$1000,"<="&EOMONTH(B6,0)) -> 1790 | E6: =SUMIFS(Data!$K$2:$K$1000,Data!$B$2:$B$1000,">="&B6,Data!$B$2:$B$1000,"<="&EOMONTH(B6,0)) -> 874378.5 | F6: =SUMIFS(Data!$M$2:$M$1000,Data!$B$2:$B$1000,">="&B6,Data!$B$2:$B$1000,"<="&EOMONTH(B6,0)) -> 200138.5 | G6: =IF(E6=0,0,F6/E6) -> 0.22889229 | H6: =IF(E5=0,"N/A",E6/E5-1) -> 0.40242865
A7: =Lists!A4 -> March | B7: =DATE(Dashboard!$C$5,MATCH(A7,Lists!$A$2:$A$13,0),1) -> 45717 | C7: =COUNTIFS(Data!$B$2:$B$1000,">="&B7,Data!$B$2:$B$1000,"<="&EOMONTH(B7,0)) -> 29 | D7: =SUMIFS(Data!$F$2:$F$1000,Data!$B$2:$B$1000,">="&B7,Data!$B$2:$B$1000,"<="&EOMONTH(B7,0)) -> 1545 | E7: =SUMIFS(Data!$K$2:$K$1000,Data!$B$2:$B$1000,">="&B7,Data!$B$2:$B$1000,"<="&EOMONTH(B7,0)) -> 1350719.5 | F7: =SUMIFS(Data!$M$2:$M$1000,Data!$B$2:$B$1000,">="&B7,Data!$B$2:$B$1000,"<="&EOMONTH(B7,0)) -> 315639.5 | G7: =IF(E7=0,0,F7/E7) -> 0.23368249 | H7: =IF(E6=0,"N/A",E7/E6-1) -> 0.54477666
A8: =Lists!A5 -> April | B8: =DATE(Dashboard!$C$5,MATCH(A8,Lists!$A$2:$A$13,0),1) -> 45748 | C8: =COUNTIFS(Data!$B$2:$B$1000,">="&B8,Data!$B$2:$B$1000,"<="&EOMONTH(B8,0)) -> 42 | D8: =SUMIFS(Data!$F$2:$F$1000,Data!$B$2:$B$1000,">="&B8,Data!$B$2:$B$1000,"<="&EOMONTH(B8,0)) -> 1862 | E8: =SUMIFS(Data!$K$2:$K$1000,Data!$B$2:$B$1000,">="&B8,Data!$B$2:$B$1000,"<="&EOMONTH(B8,0)) -> 1348972.5 | F8: =SUMIFS(Data!$M$2:$M$1000,Data!$B$2:$B$1000,">="&B8,Data!$B$2:$B$1000,"<="&EOMONTH(B8,0)) -> 317202.5 | G8: =IF(E8=0,0,F8/E8) -> 0.23514379 | H8: =IF(E7=0,"N/A",E8/E7-1) -> -0.0012933847
A9: =Lists!A6 -> May | B9: =DATE(Dashboard!$C$5,MATCH(A9,Lists!$A$2:$A$13,0),1) -> 45778 | C9: =COUNTIFS(Data!$B$2:$B$1000,">="&B9,Data!$B$2:$B$1000,"<="&EOMONTH(B9,0)) -> 31 | D9: =SUMIFS(Data!$F$2:$F$1000,Data!$B$2:$B$1000,">="&B9,Data!$B$2:$B$1000,"<="&EOMONTH(B9,0)) -> 2234 | E9: =SUMIFS(Data!$K$2:$K$1000,Data!$B$2:$B$1000,">="&B9,Data!$B$2:$B$1000,"<="&EOMONTH(B9,0)) -> 1061494 | F9: =SUMIFS(Data!$M$2:$M$1000,Data!$B$2:$B$1000,">="&B9,Data!$B$2:$B$1000,"<="&EOMONTH(B9,0)) -> 233364 | G9: =IF(E9=0,0,F9/E9) -> 0.21984486 | H9: =IF(E8=0,"N/A",E9/E8-1) -> -0.21310924
A10: =Lists!A7 -> June | B10: =DATE(Dashboard!$C$5,MATCH(A10,Lists!$A$2:$A$13,0),1) -> 45809 | C10: =COUNTIFS(Data!$B$2:$B$1000,">="&B10,Data!$B$2:$B$1000,"<="&EOMONTH(B10,0)) -> 36 | D10: =SUMIFS(Data!$F$2:$F$1000,Data!$B$2:$B$1000,">="&B10,Data!$B$2:$B$1000,"<="&EOMONTH(B10,0)) -> 2140 | E10: =SUMIFS(Data!$K$2:$K$1000,Data!$B$2:$B$1000,">="&B10,Data!$B$2:$B$1000,"<="&EOMONTH(B10,0)) -> 965288.5 | F10: =SUMIFS(Data!$M$2:$M$1000,Data!$B$2:$B$1000,">="&B10,Data!$B$2:$B$1000,"<="&EOMONTH(B10,0)) -> 228688.5 | G10: =IF(E10=0,0,F10/E10) -> 0.23691207 | H10: =IF(E9=0,"N/A",E10/E9-1) -> -0.090632166
A11: =Lists!A8 -> July | B11: =DATE(Dashboard!$C$5,MATCH(A11,Lists!$A$2:$A$13,0),1) -> 45839 | C11: =COUNTIFS(Data!$B$2:$B$1000,">="&B11,Data!$B$2:$B$1000,"<="&EOMONTH(B11,0)) -> 33 | D11: =SUMIFS(Data!$F$2:$F$1000,Data!$B$2:$B$1000,">="&B11,Data!$B$2:$B$1000,"<="&EOMONTH(B11,0)) -> 2155 | E11: =SUMIFS(Data!$K$2:$K$1000,Data!$B$2:$B$1000,">="&B11,Data!$B$2:$B$1000,"<="&EOMONTH(B11,0)) -> 976837 | F11: =SUMIFS(Data!$M$2:$M$1000,Data!$B$2:$B$1000,">="&B11,Data!$B$2:$B$1000,"<="&EOMONTH(B11,0)) -> 233097 | G11: =IF(E11=0,0,F11/E11) -> 0.23862425 | H11: =IF(E10=0,"N/A",E11/E10-1) -> 0.011963781
A12: =Lists!A9 -> August | B12: =DATE(Dashboard!$C$5,MATCH(A12,Lists!$A$2:$A$13,0),1) -> 45870 | C12: =COUNTIFS(Data!$B$2:$B$1000,">="&B12,Data!$B$2:$B$1000,"<="&EOMONTH(B12,0)) -> 41 | D12: =SUMIFS(Data!$F$2:$F$1000,Data!$B$2:$B$1000,">="&B12,Data!$B$2:$B$1000,"<="&EOMONTH(B12,0)) -> 2548 | E12: =SUMIFS(Data!$K$2:$K$1000,Data!$B$2:$B$1000,">="&B12,Data!$B$2:$B$1000,"<="&EOMONTH(B12,0)) -> 1470164.5 | F12: =SUMIFS(Data!$M$2:$M$1000,Data!$B$2:$B$1000,">="&B12,Data!$B$2:$B$1000,"<="&EOMONTH(B12,0)) -> 323414.5 | G12: =IF(E12=0,0,F12/E12) -> 0.21998525 | H12: =IF(E11=0,"N/A",E12/E11-1) -> 0.5050254
A13: =Lists!A10 -> September | B13: =DATE(Dashboard!$C$5,MATCH(A13,Lists!$A$2:$A$13,0),1) -> 45901 | C13: =COUNTIFS(Data!$B$2:$B$1000,">="&B13,Data!$B$2:$B$1000,"<="&EOMONTH(B13,0)) -> 43 | D13: =SUMIFS(Data!$F$2:$F$1000,Data!$B$2:$B$1000,">="&B13,Data!$B$2:$B$1000,"<="&EOMONTH(B13,0)) -> 2519 | E13: =SUMIFS(Data!$K$2:$K$1000,Data!$B$2:$B$1000,">="&B13,Data!$B$2:$B$1000,"<="&EOMONTH(B13,0)) -> 1598769 | F13: =SUMIFS(Data!$M$2:$M$1000,Data!$B$2:$B$1000,">="&B13,Data!$B$2:$B$1000,"<="&EOMONTH(B13,0)) -> 373269 | G13: =IF(E13=0,0,F13/E13) -> 0.23347275 | H13: =IF(E12=0,"N/A",E13/E12-1) -> 0.087476265
A14: =Lists!A11 -> October | B14: =DATE(Dashboard!$C$5,MATCH(A14,Lists!$A$2:$A$13,0),1) -> 45931 | C14: =COUNTIFS(Data!$B$2:$B$1000,">="&B14,Data!$B$2:$B$1000,"<="&EOMONTH(B14,0)) -> 64 | D14: =SUMIFS(Data!$F$2:$F$1000,Data!$B$2:$B$1000,">="&B14,Data!$B$2:$B$1000,"<="&EOMONTH(B14,0)) -> 3612 | E14: =SUMIFS(Data!$K$2:$K$1000,Data!$B$2:$B$1000,">="&B14,Data!$B$2:$B$1000,"<="&EOMONTH(B14,0)) -> 3096570 | F14: =SUMIFS(Data!$M$2:$M$1000,Data!$B$2:$B$1000,">="&B14,Data!$B$2:$B$1000,"<="&EOMONTH(B14,0)) -> 662190 | G14: =IF(E14=0,0,F14/E14) -> 0.21384629 | H14: =IF(E13=0,"N/A",E14/E13-1) -> 0.93684641
A15: =Lists!A12 -> November | B15: =DATE(Dashboard!$C$5,MATCH(A15,Lists!$A$2:$A$13,0),1) -> 45962 | C15: =COUNTIFS(Data!$B$2:$B$1000,">="&B15,Data!$B$2:$B$1000,"<="&EOMONTH(B15,0)) -> 58 | D15: =SUMIFS(Data!$F$2:$F$1000,Data!$B$2:$B$1000,">="&B15,Data!$B$2:$B$1000,"<="&EOMONTH(B15,0)) -> 2898 | E15: =SUMIFS(Data!$K$2:$K$1000,Data!$B$2:$B$1000,">="&B15,Data!$B$2:$B$1000,"<="&EOMONTH(B15,0)) -> 2434754 | F15: =SUMIFS(Data!$M$2:$M$1000,Data!$B$2:$B$1000,">="&B15,Data!$B$2:$B$1000,"<="&EOMONTH(B15,0)) -> 561944 | G15: =IF(E15=0,0,F15/E15) -> 0.23080114 | H15: =IF(E14=0,"N/A",E15/E14-1) -> -0.21372551
A16: =Lists!A13 -> December | B16: =DATE(Dashboard!$C$5,MATCH(A16,Lists!$A$2:$A$13,0),1) -> 45992 | C16: =COUNTIFS(Data!$B$2:$B$1000,">="&B16,Data!$B$2:$B$1000,"<="&EOMONTH(B16,0)) -> 49 | D16: =SUMIFS(Data!$F$2:$F$1000,Data!$B$2:$B$1000,">="&B16,Data!$B$2:$B$1000,"<="&EOMONTH(B16,0)) -> 2906 | E16: =SUMIFS(Data!$K$2:$K$1000,Data!$B$2:$B$1000,">="&B16,Data!$B$2:$B$1000,"<="&EOMONTH(B16,0)) -> 1772546.5 | F16: =SUMIFS(Data!$M$2:$M$1000,Data!$B$2:$B$1000,">="&B16,Data!$B$2:$B$1000,"<="&EOMONTH(B16,0)) -> 378206.5 | G16: =IF(E16=0,0,F16/E16) -> 0.21336901 | H16: =IF(E15=0,"N/A",E16/E15-1) -> -0.27198128
A17: Year Total | C17: =SUM(C5:C16) -> 480 | D17: =SUM(D5:D16) -> 27503 | E17: =SUM(E5:E16) -> 17573968 | F17: =SUM(F5:F16) -> 3983488.5 | G17: =IF(E17=0,0,F17/E17) -> 0.22666983

Sheet Data
A1: Order ID | B1: Order Date | C1: Region | D1: Salesperson | E1: Product | F1: Qty | G1: Discount % | H1: Category (lookup) | I1: Unit Price (lookup) | J1: Unit Cost (lookup) | K1: Sales Amount | L1: Cost | M1: Profit
A2: ORD-2025-0001 | B2: 45660 | C2: North | D2: Neha Sharma | E2: Water Dispenser | F2: 10 | G2: 0.05 | H2: =IF($A2="","",IFERROR(INDEX(Products!$B$2:$B$50,MATCH($E2,Products!$A$2:$A$50,0)),"Unmapped")) -> Pantry | I2: =IF($A2="","",IFERROR(INDEX(Products!$C$2:$C$50,MATCH($E2,Products!$A$2:$A$50,0)),0)) -> 5600 | J2: =IF($A2="","",IFERROR(INDEX(Products!$D$2:$D$50,MATCH($E2,Products!$A$2:$A$50,0)),0)) -> 4200 | K2: =IF($A2="","",$F2*$I2*(1-$G2)) -> 53200 | L2: =IF($A2="","",$F2*$J2) -> 42000 | M2: =IF($A2="","",$K2-$L2) -> 11200
A3: ORD-2025-0002 | B3: 45661 | C3: South | D3: Priya Nair | E3: Notebook Pack | F3: 148 | G3: 0.15 | H3: =IF($A3="","",IFERROR(INDEX(Products!$B$2:$B$50,MATCH($E3,Products!$A$2:$A$50,0)),"Unmapped")) -> Stationery | I3: =IF($A3="","",IFERROR(INDEX(Products!$C$2:$C$50,MATCH($E3,Products!$A$2:$A$50,0)),0)) -> 350 | J3: =IF($A3="","",IFERROR(INDEX(Products!$D$2:$D$50,MATCH($E3,Products!$A$2:$A$50,0)),0)) -> 240 | K3: =IF($A3="","",$F3*$I3*(1-$G3)) -> 44030 | L3: =IF($A3="","",$F3*$J3) -> 35520 | M3: =IF($A3="","",$K3-$L3) -> 8510
A4: ORD-2025-0003 | B4: 45667 | C4: North | D4: Amit Verma | E4: Notebook Pack | F4: 144 | G4: 0 | H4: =IF($A4="","",IFERROR(INDEX(Products!$B$2:$B$50,MATCH($E4,Products!$A$2:$A$50,0)),"Unmapped")) -> Stationery | I4: =IF($A4="","",IFERROR(INDEX(Products!$C$2:$C$50,MATCH($E4,Products!$A$2:$A$50,0)),0)) -> 350 | J4: =IF($A4="","",IFERROR(INDEX(Products!$D$2:$D$50,MATCH($E4,Products!$A$2:$A$50,0)),0)) -> 240 | K4: =IF($A4="","",$F4*$I4*(1-$G4)) -> 50400 | L4: =IF($A4="","",$F4*$J4) -> 34560 | M4: =IF($A4="","",$K4-$L4) -> 15840
A5: ORD-2025-0004 | B5: 45668 | C5: East | D5: Vikram Roy | E5: Ball Pens Box | F5: 133 | G5: 0.05 | H5: =IF($A5="","",IFERROR(INDEX(Products!$B$2:$B$50,MATCH($E5,Products!$A$2:$A$50,0)),"Unmapped")) -> Stationery | I5: =IF($A5="","",IFERROR(INDEX(Products!$C$2:$C$50,MATCH($E5,Products!$A$2:$A$50,0)),0)) -> 120 | J5: =IF($A5="","",IFERROR(INDEX(Products!$D$2:$D$50,MATCH($E5,Products!$A$2:$A$50,0)),0)) -> 80 | K5: =IF($A5="","",$F5*$I5*(1-$G5)) -> 15162 | L5: =IF($A5="","",$F5*$J5) -> 10640 | M5: =IF($A5="","",$K5-$L5) -> 4522
A6: ORD-2025-0005 | B6: 45668 | C6: East | D6: Vikram Roy | E6: Notebook Pack | F6: 130 | G6: 0 | H6: =IF($A6="","",IFERROR(INDEX(Products!$B$2:$B$50,MATCH($E6,Products!$A$2:$A$50,0)),"Unmapped")) -> Stationery | I6: =IF($A6="","",IFERROR(INDEX(Products!$C$2:$C$50,MATCH($E6,Products!$A$2:$A$50,0)),0)) -> 350 | J6: =IF($A6="","",IFERROR(INDEX(Products!$D$2:$D$50,MATCH($E6,Products!$A$2:$A$50,0)),0)) -> 240 | K6: =IF($A6="","",$F6*$I6*(1-$G6)) -> 45500 | L6: =IF($A6="","",$F6*$J6) -> 31200 | M6: =IF($A6="","",$K6-$L6) -> 14300
A7: ORD-2025-0006 | B7: 45670 | C7: South | D7: Karan Iyer | E7: A4 Paper Ream | F7: 22 | G7: 0.1 | H7: =IF($A7="","",IFERROR(INDEX(Products!$B$2:$B$50,MATCH($E7,Products!$A$2:$A$50,0)),"Unmapped")) -> Stationery | I7: =IF($A7="","",IFERROR(INDEX(Products!$C$2:$C$50,MATCH($E7,Products!$A$2:$A$50,0)),0)) -> 280 | J7: =IF($A7="","",IFERROR(INDEX(Products!$D$2:$D$50,MATCH($E7,Products!$A$2:$A$50,0)),0)) -> 210 | K7: =IF($A7="","",$F7*$I7*(1-$G7)) -> 5544 | L7: =IF($A7="","",$F7*$J7) -> 4620 | M7: =IF($A7="","",$K7-$L7) -> 924
A8: ORD-2025-0007 | B8: 45670 | C8: East | D8: Vikram Roy | E8: Office Chair | F8: 13 | G8: 0.05 | H8: =IF($A8="","",IFERROR(INDEX(Products!$B$2:$B$50,MATCH($E8,Products!$A$2:$A$50,0)),"Unmapped")) -> Furniture | I8: =IF($A8="","",IFERROR(INDEX(Products!$C$2:$C$50,MATCH($E8,Products!$A$2:$A$50,0)),0)) -> 4800 | J8: =IF($A8="","",IFERROR(INDEX(Products!$D$2:$D$50,MATCH($E8,Products!$A$2:$A$50,0)),0)) -> 3500 | K8: =IF($A8="","",$F8*$I8*(1-$G8)) -> 59280 | L8: =IF($A8="","",$F8*$J8) -> 45500 | M8: =IF($A8="","",$K8-$L8) -> 13780
A9: ORD-2025-0008 | B9: 45671 | C9: North | D9: Amit Verma | E9: Notebook Pack | F9: 37 | G9: 0.15 | H9: =IF($A9="","",IFERROR(INDEX(Products!$B$2:$B$50,MATCH($E9,Products!$A$2:$A$50,0)),"Unmapped")) -> Stationery | I9: =IF($A9="","",IFERROR(INDEX(Products!$C$2:$C$50,MATCH($E9,Products!$A$2:$A$50,0)),0)) -> 350 | J9: =IF($A9="","",IFERROR(INDEX(Products!$D$2:$D$50,MATCH($E9,Products!$A$2:$A$50,0)),0)) -> 240 | K9: =IF($A9="","",$F9*$I9*(1-$G9)) -> 11007.5 | L9: =IF($A9="","",$F9*$J9) -> 8880 | M9: =IF($A9="","",$K9-$L9) -> 2127.5
A10: ORD-2025-0009 | B10: 45673 | C10: North | D10: Neha Sharma | E10: Notebook Pack | F10: 78 | G10: 0 | H10: =IF($A10="","",IFERROR(INDEX(Products!$B$2:$B$50,MATCH($E10,Products!$A$2:$A$50,0)),"Unmapped")) -> Stationery | I10: =IF($A10="","",IFERROR(INDEX(Products!$C$2:$C$50,MATCH($E10,Products!$A$2:$A$50,0)),0)) -> 350 | J10: =IF($A10="","",IFERROR(INDEX(Products!$D$2:$D$50,MATCH($E10,Products!$A$2:$A$50,0)),0)) -> 240 | K10: =IF($A10="","",$F10*$I10*(1-$G10)) -> 27300 | L10: =IF($A10="","",$F10*$J10) -> 18720 | M10: =IF($A10="","",$K10-$L10) -> 8580
A11: ORD-2025-0010 | B11: 45673 | C11: North | D11: Amit Verma | E11: Ball Pens Box | F11: 164 | G11: 0.15 | H11: =IF($A11="","",IFERROR(INDEX(Products!$B$2:$B$50,MATCH($E11,Products!$A$2:$A$50,0)),"Unmapped")) -> Stationery | I11: =IF($A11="","",IFERROR(INDEX(Products!$C$2:$C$50,MATCH($E11,Products!$A$2:$A$50,0)),0)) -> 120 | J11: =IF($A11="","",IFERROR(INDEX(Products!$D$2:$D$50,MATCH($E11,Products!$A$2:$A$50,0)),0)) -> 80 | K11: =IF($A11="","",$F11*$I11*(1-$G11)) -> 16728 | L11: =IF($A11="","",$F11*$J11) -> 13120 | M11: =IF($A11="","",$K11-$L11) -> 3608
A12: ORD-2025-0011 | B12: 45674 | C12: South | D12: Priya Nair | E12: Ball Pens Box | F12: 20 | G12: 0.05 | H12: =IF($A12="","",IFERROR(INDEX(Products!$B$2:$B$50,MATCH($E12,Products!$A$2:$A$50,0)),"Unmapped")) -> Stationery | I12: =IF($A12="","",IFERROR(INDEX(Products!$C$2:$C$50,MATCH($E12,Products!$A$2:$A$50,0)),0)) -> 120 | J12: =IF($A12="","",IFERROR(INDEX(Products!$D$2:$D$50,MATCH($E12,Products!$A$2:$A$50,0)),0)) -> 80 | K12: =IF($A12="","",$F12*$I12*(1-$G12)) -> 2280 | L12: =IF($A12="","",$F12*$J12) -> 1600 | M12: =IF($A12="","",$K12-$L12) -> 680
A13: ORD-2025-0012 | B13: 45674 | C13: East | D13: Vikram Roy | E13: A4 Paper Ream | F13: 198 | G13: 0.05 | H13: =IF($A13="","",IFERROR(INDEX(Products!$B$2:$B$50,MATCH($E13,Products!$A$2:$A$50,0)),"Unmapped")) -> Stationery | I13: =IF($A13="","",IFERROR(INDEX(Products!$C$2:$C$50,MATCH($E13,Products!$A$2:$A$50,0)),0)) -> 280 | J13: =IF($A13="","",IFERROR(INDEX(Products!$D$2:$D$50,MATCH($E13,Products!$A$2:$A$50,0)),0)) -> 210 | K13: =IF($A13="","",$F13*$I13*(1-$G13)) -> 52668 | L13: =IF($A13="","",$F13*$J13) -> 41580 | M13: =IF($A13="","",$K13-$L13) -> 11088
... A481: ORD-2025-0480 | B481: 46021 | C481: West | D481: Anjali Joshi | E481: Work Desk | F481: 3 | G481: 0 | H481: =IF($A481="","",IFERROR(INDEX(Products!$B$2:$B$50,MATCH($E481,Products!$A$2:$A$50,0)),"Unmapped")) -> Furniture | I481: =IF($A481="","",IFERROR(INDEX(Products!$C$2:$C$50,MATCH($E481,Products!$A$2:$A$50,0)),0)) -> 7200 | J481: =IF($A481="","",IFERROR(INDEX(Products!$D$2:$D$50,MATCH($E481,Products!$A$2:$A$50,0)),0)) -> 5400 | K481: =IF($A481="","",$F481*$I481*(1-$G481)) -> 21600 | L481: =IF($A481="","",$F481*$J481) -> 16200 | M481: =IF($A481="","",$K481-$L481) -> 5400
H482: =IF($A482="","",IFERROR(INDEX(Products!$B$2:$B$50,MATCH($E482,Products!$A$2:$A$50,0)),"Unmapped")) | I482: =IF($A482="","",IFERROR(INDEX(Products!$C$2:$C$50,MATCH($E482,Products!$A$2:$A$50,0)),0)) | J482: =IF($A482="","",IFERROR(INDEX(Products!$D$2:$D$50,MATCH($E482,Products!$A$2:$A$50,0)),0)) | K482: =IF($A482="","",$F482*$I482*(1-$G482)) | L482: =IF($A482="","",$F482*$J482) | M482: =IF($A482="","",$K482-$L482)
H483: =IF($A483="","",IFERROR(INDEX(Products!$B$2:$B$50,MATCH($E483,Products!$A$2:$A$50,0)),"Unmapped")) | I483: =IF($A483="","",IFERROR(INDEX(Products!$C$2:$C$50,MATCH($E483,Products!$A$2:$A$50,0)),0)) | J483: =IF($A483="","",IFERROR(INDEX(Products!$D$2:$D$50,MATCH($E483,Products!$A$2:$A$50,0)),0)) | K483: =IF($A483="","",$F483*$I483*(1-$G483)) | L483: =IF($A483="","",$F483*$J483) | M483: =IF($A483="","",$K483-$L483)
H484: =IF($A484="","",IFERROR(INDEX(Products!$B$2:$B$50,MATCH($E484,Products!$A$2:$A$50,0)),"Unmapped")) | I484: =IF($A484="","",IFERROR(INDEX(Products!$C$2:$C$50,MATCH($E484,Products!$A$2:$A$50,0)),0)) | J484: =IF($A484="","",IFERROR(INDEX(Products!$D$2:$D$50,MATCH($E484,Products!$A$2:$A$50,0)),0)) | K484: =IF($A484="","",$F484*$I484*(1-$G484)) | L484: =IF($A484="","",$F484*$J484) | M484: =IF($A484="","",$K484-$L484)
H485: =IF($A485="","",IFERROR(INDEX(Products!$B$2:$B$50,MATCH($E485,Products!$A$2:$A$50,0)),"Unmapped")) | I485: =IF($A485="","",IFERROR(INDEX(Products!$C$2:$C$50,MATCH($E485,Products!$A$2:$A$50,0)),0)) | J485: =IF($A485="","",IFERROR(INDEX(Products!$D$2:$D$50,MATCH($E485,Products!$A$2:$A$50,0)),0)) | K485: =IF($A485="","",$F485*$I485*(1-$G485)) | L485: =IF($A485="","",$F485*$J485) | M485: =IF($A485="","",$K485-$L485)
H486: =IF($A486="","",IFERROR(INDEX(Products!$B$2:$B$50,MATCH($E486,Products!$A$2:$A$50,0)),"Unmapped")) | I486: =IF($A486="","",IFERROR(INDEX(Products!$C$2:$C$50,MATCH($E486,Products!$A$2:$A$50,0)),0)) | J486: =IF($A486="","",IFERROR(INDEX(Products!$D$2:$D$50,MATCH($E486,Products!$A$2:$A$50,0)),0)) | K486: =IF($A486="","",$F486*$I486*(1-$G486)) | L486: =IF($A486="","",$F486*$J486) | M486: =IF($A486="","",$K486-$L486)
H487: =IF($A487="","",IFERROR(INDEX(Products!$B$2:$B$50,MATCH($E487,Products!$A$2:$A$50,0)),"Unmapped")) | I487: =IF($A487="","",IFERROR(INDEX(Products!$C$2:$C$50,MATCH($E487,Products!$A$2:$A$50,0)),0)) | J487: =IF($A487="","",IFERROR(INDEX(Products!$D$2:$D$50,MATCH($E487,Products!$A$2:$A$50,0)),0)) | K487: =IF($A487="","",$F487*$I487*(1-$G487)) | L487: =IF($A487="","",$F487*$J487) | M487: =IF($A487="","",$K487-$L487)
H488: =IF($A488="","",IFERROR(INDEX(Products!$B$2:$B$50,MATCH($E488,Products!$A$2:$A$50,0)),"Unmapped")) | I488: =IF($A488="","",IFERROR(INDEX(Products!$C$2:$C$50,MATCH($E488,Products!$A$2:$A$50,0)),0)) | J488: =IF($A488="","",IFERROR(INDEX(Products!$D$2:$D$50,MATCH($E488,Products!$A$2:$A$50,0)),0)) | K488: =IF($A488="","",$F488*$I488*(1-$G488)) | L488: =IF($A488="","",$F488*$J488) | M488: =IF($A488="","",$K488-$L488)
H489: =IF($A489="","",IFERROR(INDEX(Products!$B$2:$B$50,MATCH($E489,Products!$A$2:$A$50,0)),"Unmapped")) | I489: =IF($A489="","",IFERROR(INDEX(Products!$C$2:$C$50,MATCH($E489,Products!$A$2:$A$50,0)),0)) | J489: =IF($A489="","",IFERROR(INDEX(Products!$D$2:$D$50,MATCH($E489,Products!$A$2:$A$50,0)),0)) | K489: =IF($A489="","",$F489*$I489*(1-$G489)) | L489: =IF($A489="","",$F489*$J489) | M489: =IF($A489="","",$K489-$L489)
H490: =IF($A490="","",IFERROR(INDEX(Products!$B$2:$B$50,MATCH($E490,Products!$A$2:$A$50,0)),"Unmapped")) | I490: =IF($A490="","",IFERROR(INDEX(Products!$C$2:$C$50,MATCH($E490,Products!$A$2:$A$50,0)),0)) | J490: =IF($A490="","",IFERROR(INDEX(Products!$D$2:$D$50,MATCH($E490,Products!$A$2:$A$50,0)),0)) | K490: =IF($A490="","",$F490*$I490*(1-$G490)) | L490: =IF($A490="","",$F490*$J490) | M490: =IF($A490="","",$K490-$L490)
H491: =IF($A491="","",IFERROR(INDEX(Products!$B$2:$B$50,MATCH($E491,Products!$A$2:$A$50,0)),"Unmapped")) | I491: =IF($A491="","",IFERROR(INDEX(Products!$C$2:$C$50,MATCH($E491,Products!$A$2:$A$50,0)),0)) | J491: =IF($A491="","",IFERROR(INDEX(Products!$D$2:$D$50,MATCH($E491,Products!$A$2:$A$50,0)),0)) | K491: =IF($A491="","",$F491*$I491*(1-$G491)) | L491: =IF($A491="","",$F491*$J491) | M491: =IF($A491="","",$K491-$L491)
H492: =IF($A492="","",IFERROR(INDEX(Products!$B$2:$B$50,MATCH($E492,Products!$A$2:$A$50,0)),"Unmapped")) | I492: =IF($A492="","",IFERROR(INDEX(Products!$C$2:$C$50,MATCH($E492,Products!$A$2:$A$50,0)),0)) | J492: =IF($A492="","",IFERROR(INDEX(Products!$D$2:$D$50,MATCH($E492,Products!$A$2:$A$50,0)),0)) | K492: =IF($A492="","",$F492*$I492*(1-$G492)) | L492: =IF($A492="","",$F492*$J492) | M492: =IF($A492="","",$K492-$L492)
H493: =IF($A493="","",IFERROR(INDEX(Products!$B$2:$B$50,MATCH($E493,Products!$A$2:$A$50,0)),"Unmapped")) | I493: =IF($A493="","",IFERROR(INDEX(Products!$C$2:$C$50,MATCH($E493,Products!$A$2:$A$50,0)),0)) | J493: =IF($A493="","",IFERROR(INDEX(Products!$D$2:$D$50,MATCH($E493,Products!$A$2:$A$50,0)),0)) | K493: =IF($A493="","",$F493*$I493*(1-$G493)) | L493: =IF($A493="","",$F493*$J493) | M493: =IF($A493="","",$K493-$L493)
... H1000: =IF($A1000="","",IFERROR(INDEX(Products!$B$2:$B$50,MATCH($E1000,Products!$A$2:$A$50,0)),"Unmapped")) | I1000: =IF($A1000="","",IFERROR(INDEX(Products!$C$2:$C$50,MATCH($E1000,Products!$A$2:$A$50,0)),0)) | J1000: =IF($A1000="","",IFERROR(INDEX(Products!$D$2:$D$50,MATCH($E1000,Products!$A$2:$A$50,0)),0)) | K1000: =IF($A1000="","",$F1000*$I1000*(1-$G1000)) | L1000: =IF($A1000="","",$F1000*$J1000) | M1000: =IF($A1000="","",$K1000-$L1000)

Sheet Products
A1: Product | B1: Category | C1: Unit Price (₹) | D1: Unit Cost (₹)
A2: A4 Paper Ream | B2: Stationery | C2: 280 | D2: 210
A3: Ball Pens Box | B3: Stationery | C3: 120 | D3: 80
A4: Notebook Pack | B4: Stationery | C4: 350 | D4: 240
A5: Office Chair | B5: Furniture | C5: 4800 | D5: 3500
A6: Work Desk | B6: Furniture | C6: 7200 | D6: 5400
A7: Filing Cabinet | B7: Furniture | C7: 6100 | D7: 4500
A8: Wireless Mouse | B8: Electronics | C8: 650 | D8: 430
A9: Keyboard | B9: Electronics | C9: 900 | D9: 620
A10: Printer | B10: Electronics | C10: 9800 | D10: 7600
A11: LED Monitor | B11: Electronics | C11: 8900 | D11: 7000
A12: Tea Premix Carton | B12: Pantry | C12: 1500 | D12: 1100
A13: Water Dispenser | B13: Pantry | C13: 5600 | D13: 4200
A15: Assumption: unit prices and costs are assumed sample values for a fictional office-supplies distributor (not real company data). Add new products in rows 14-50 and they are picked up automatically.

Sheet Lists
A1: Months | B1: Regions | C1: Salespersons | D1: Person's Region | E1: Categories | F1: Sales - selected month (helper) | G1: Orders - selected month (helper) | H1: Rank (helper)
A2: January | B2: North | C2: Amit Verma | D2: North | E2: Stationery | F2: =SUMIFS(Data!$K$2:$K$1000,Data!$D$2:$D$1000,$C2,Data!$B$2:$B$1000,">="&Dashboard!$C$6,Data!$B$2:$B$1000,"<="&Dashboard!$F$6) -> 544835 | G2: =COUNTIFS(Data!$D$2:$D$1000,$C2,Data!$B$2:$B$1000,">="&Dashboard!$C$6,Data!$B$2:$B$1000,"<="&Dashboard!$F$6) -> 12 | H2: =RANK(F2,$F$2:$F$9)+COUNTIF($F$2:F2,F2)-1 -> 1
A3: February | B3: South | C3: Neha Sharma | D3: North | E3: Furniture | F3: =SUMIFS(Data!$K$2:$K$1000,Data!$D$2:$D$1000,$C3,Data!$B$2:$B$1000,">="&Dashboard!$C$6,Data!$B$2:$B$1000,"<="&Dashboard!$F$6) -> 188358 | G3: =COUNTIFS(Data!$D$2:$D$1000,$C3,Data!$B$2:$B$1000,">="&Dashboard!$C$6,Data!$B$2:$B$1000,"<="&Dashboard!$F$6) -> 7 | H3: =RANK(F3,$F$2:$F$9)+COUNTIF($F$2:F3,F3)-1 -> 4
A4: March | B4: East | C4: Priya Nair | D4: South | E4: Electronics | F4: =SUMIFS(Data!$K$2:$K$1000,Data!$D$2:$D$1000,$C4,Data!$B$2:$B$1000,">="&Dashboard!$C$6,Data!$B$2:$B$1000,"<="&Dashboard!$F$6) -> 228155 | G4: =COUNTIFS(Data!$D$2:$D$1000,$C4,Data!$B$2:$B$1000,">="&Dashboard!$C$6,Data!$B$2:$B$1000,"<="&Dashboard!$F$6) -> 4 | H4: =RANK(F4,$F$2:$F$9)+COUNTIF($F$2:F4,F4)-1 -> 3
A5: April | B5: West | C5: Karan Iyer | D5: South | E5: Pantry | F5: =SUMIFS(Data!$K$2:$K$1000,Data!$D$2:$D$1000,$C5,Data!$B$2:$B$1000,">="&Dashboard!$C$6,Data!$B$2:$B$1000,"<="&Dashboard!$F$6) -> 396817 | G5: =COUNTIFS(Data!$D$2:$D$1000,$C5,Data!$B$2:$B$1000,">="&Dashboard!$C$6,Data!$B$2:$B$1000,"<="&Dashboard!$F$6) -> 12 | H5: =RANK(F5,$F$2:$F$9)+COUNTIF($F$2:F5,F5)-1 -> 2
A6: May | C6: Sneha Das | D6: East | F6: =SUMIFS(Data!$K$2:$K$1000,Data!$D$2:$D$1000,$C6,Data!$B$2:$B$1000,">="&Dashboard!$C$6,Data!$B$2:$B$1000,"<="&Dashboard!$F$6) -> 24444 | G6: =COUNTIFS(Data!$D$2:$D$1000,$C6,Data!$B$2:$B$1000,">="&Dashboard!$C$6,Data!$B$2:$B$1000,"<="&Dashboard!$F$6) -> 2 | H6: =RANK(F6,$F$2:$F$9)+COUNTIF($F$2:F6,F6)-1 -> 7
A7: June | C7: Vikram Roy | D7: East | F7: =SUMIFS(Data!$K$2:$K$1000,Data!$D$2:$D$1000,$C7,Data!$B$2:$B$1000,">="&Dashboard!$C$6,Data!$B$2:$B$1000,"<="&Dashboard!$F$6) -> 58630 | G7: =COUNTIFS(Data!$D$2:$D$1000,$C7,Data!$B$2:$B$1000,">="&Dashboard!$C$6,Data!$B$2:$B$1000,"<="&Dashboard!$F$6) -> 2 | H7: =RANK(F7,$F$2:$F$9)+COUNTIF($F$2:F7,F7)-1 -> 6
A8: July | C8: Anjali Joshi | D8: West | F8: =SUMIFS(Data!$K$2:$K$1000,Data!$D$2:$D$1000,$C8,Data!$B$2:$B$1000,">="&Dashboard!$C$6,Data!$B$2:$B$1000,"<="&Dashboard!$F$6) -> 0 | G8: =COUNTIFS(Data!$D$2:$D$1000,$C8,Data!$B$2:$B$1000,">="&Dashboard!$C$6,Data!$B$2:$B$1000,"<="&Dashboard!$F$6) -> 0 | H8: =RANK(F8,$F$2:$F$9)+COUNTIF($F$2:F8,F8)-1 -> 8
A9: August | C9: Rohit Patil | D9: West | F9: =SUMIFS(Data!$K$2:$K$1000,Data!$D$2:$D$1000,$C9,Data!$B$2:$B$1000,">="&Dashboard!$C$6,Data!$B$2:$B$1000,"<="&Dashboard!$F$6) -> 157530 | G9: =COUNTIFS(Data!$D$2:$D$1000,$C9,Data!$B$2:$B$1000,">="&Dashboard!$C$6,Data!$B$2:$B$1000,"<="&Dashboard!$F$6) -> 4 | H9: =RANK(F9,$F$2:$F$9)+COUNTIF($F$2:F9,F9)-1 -> 5
A10: September
A11: October
A12: November
A13: December
A15: Blue = editable lists used by dropdowns and tables. Columns F-H are helper formulas for the Top 5 table (do not edit).

Sheet Data_Checks
A1: Data Validation Checks
A2: Overall status: | B2: =IF(COUNTIF(C5:C16,"REVIEW")=0,"ALL CHECKS PASSED","REVIEW NEEDED") -> ALL CHECKS PASSED
A4: Check | B4: Result | C4: Status | D4: What it means
A5: Total order records | B5: =COUNTA(Data!$A$2:$A$1000) -> 480 | C5: =IF(B5>0,"PASS","REVIEW") -> PASS | D5: Number of orders loaded in the Data sheet (must be above 0).
A6: Orders with missing date | B6: =SUMPRODUCT((Data!$A$2:$A$1000<>"")*(Data!$B$2:$B$1000="")) -> 0 | C6: =IF(B6=0,"PASS","REVIEW") -> PASS | D6: Order ID present but Order Date blank.
A7: Orders with missing region or salesperson | B7: =SUMPRODUCT((Data!$A$2:$A$1000<>"")*(((Data!$C$2:$C$1000="")+(Data!$D$2:$D$1000=""))>0)) -> 0 | C7: =IF(B7=0,"PASS","REVIEW") -> PASS | D7: Region or Salesperson left blank.
A8: Orders with missing product or quantity | B8: =SUMPRODUCT((Data!$A$2:$A$1000<>"")*(((Data!$E$2:$E$1000="")+(Data!$F$2:$F$1000=""))>0)) -> 0 | C8: =IF(B8=0,"PASS","REVIEW") -> PASS | D8: Product or Qty left blank.
A9: Duplicate order IDs | B9: =SUMPRODUCT((Data!$A$2:$A$1000<>"")*(COUNTIF(Data!$A$2:$A$1000,Data!$A$2:$A$1000)>1)) -> 0 | C9: =IF(B9=0,"PASS","REVIEW") -> PASS | D9: Same Order ID entered more than once.
A10: Quantity zero or negative | B10: =COUNTIFS(Data!$F$2:$F$1000,"<=0") -> 0 | C10: =IF(B10=0,"PASS","REVIEW") -> PASS | D10: Qty must be a positive number.
A11: Discount outside 0%-50% | B11: =COUNTIFS(Data!$G$2:$G$1000,"<0")+COUNTIFS(Data!$G$2:$G$1000,">0.5") -> 0 | C11: =IF(B11=0,"PASS","REVIEW") -> PASS | D11: Discount looks wrong (negative or above 50%).
A12: Products missing from Products sheet | B12: =COUNTIF(Data!$H$2:$H$1000,"Unmapped") -> 0 | C12: =IF(B12=0,"PASS","REVIEW") -> PASS | D12: Product name not found in the product master, so price and cost are 0.
A13: Order dates outside the report year | B13: =SUMPRODUCT((Data!$B$2:$B$1000<>"")*(YEAR(Data!$B$2:$B$1000)<>Dashboard!$C$5)) -> 0 | C13: =IF(B13=0,"PASS","REVIEW") -> PASS | D13: Dates that fall outside the year chosen on the Dashboard.
A14: Region total minus KPI total (selected month) | B14: =ROUND(Dashboard!C18-Dashboard!B9,2) -> 0 | C14: =IF(B14=0,"PASS","REVIEW") -> PASS | D14: Reconciliation: region table must equal Total Sales.
A15: Category total minus KPI total (selected month) | B15: =ROUND(Dashboard!I18-Dashboard!B9,2) -> 0 | C15: =IF(B15=0,"PASS","REVIEW") -> PASS | D15: Reconciliation: category table must equal Total Sales.
A16: Monthly summary total minus all Data sales | B16: =ROUND(Monthly_Summary!E17-SUM(Data!$K$2:$K$1000),2) -> 0 | C16: =IF(B16=0,"PASS","REVIEW") -> PASS | D16: Reconciliation: yearly total must equal the sum of all orders.
